openaihub/__init__.py
openaihub/cli.py
openaihub/func/__init__.py
openaihub-0.1.0.dist-info/LICENSE
openaihub-0.1.0.dist-info/METADATA
openaihub-0.1.0.dist-info/WHEEL
openaihub-0.1.0.dist-info/entry_points.txt
openaihub-0.1.0.dist-info/top_level.txt
openaihub-0.1.0.dist-info/RECORD
